WebGenie/__init__.py
WebGenie/__main__.py
WebGenie-0.1.0.dist-info/METADATA
WebGenie-0.1.0.dist-info/WHEEL
WebGenie-0.1.0.dist-info/entry_points.txt
WebGenie-0.1.0.dist-info/top_level.txt
WebGenie-0.1.0.dist-info/RECORD
